fucktop.py
fucktop-3.1.0.dist-info/METADATA
fucktop-3.1.0.dist-info/WHEEL
fucktop-3.1.0.dist-info/top_level.txt
fucktop-3.1.0.dist-info/RECORD
