Metadata-Version: 2.1
Name: fucktop
Version: 3.1.0
Summary: 一个免费而热搜工具(喜欢关注:python学霸微信公众号)
Home-page: UNKNOWN
Author: Python学霸
Author-email: python@xueba.com
License: UNKNOWN
Platform: UNKNOWN
Requires-Dist: mechanicalsoup
